two_player_game.v
`timescale 1ns / 1ps


module two_player_game(
    input clk, reset,
    input [2:0] action_player1, action_player2,
    output reg [1:0] health_player1, health_player2,
    output reg [2:0] position_player1, position_player2
);

// Define states for actions
parameter MOVE_LEFT = 3'b000, MOVE_RIGHT = 3'b001, JUMP = 3'b010, WAIT = 3'b011, PUNCH = 3'b100, KICK = 3'b101;

// State registers for both players
reg [2:0] state_player1, state_player2, last_action_player1, last_action_player2;

// Initialize players' states, health, positions, and last actions
initial begin
    health_player1 = 3;  // 3 health points
    health_player2 = 3;
    position_player1 = 0;  // Starting positions
    position_player2 = 5;
    state_player1 = WAIT;  // Starting state
    state_player2 = WAIT;
    last_action_player1 = WAIT;
    last_action_player2 = WAIT;
end

// State transition logic with clock and reset
always @(posedge clk or posedge reset) begin
    if (reset) begin
        // Resetting health, positions, and last actions
        health_player1 <= 3;
        health_player2 <= 3;
        position_player1 <= 0;
        position_player2 <= 5;
        state_player1 <= WAIT;
        state_player2 <= WAIT;
        last_action_player1 <= WAIT;
        last_action_player2 <= WAIT;
    end else begin
        // Update states based on actions
        state_player1 <= action_player1;
        state_player2 <= action_player2;
    end
end

// Game logic to handle interactions, health changes, and special rules
always @(posedge clk) begin
    // Handling movement
    if (state_player1 == MOVE_LEFT && position_player1 > 0) position_player1 <= (position_player1 - 1);
    else if (state_player1 == MOVE_RIGHT && position_player1 < 2) position_player1 <= (position_player1 + 1);
    if (state_player2 == MOVE_LEFT && position_player2 > 3) position_player2 <= (position_player2 - 1);
    else if (state_player2 == MOVE_RIGHT && position_player2 < 5) position_player2 <= (position_player2 + 1);

    // Handling attacks and health reduction
    if (position_player2 - position_player1 == 1) begin
        // Punch takes precedence over kick
        if (state_player1 == PUNCH && state_player2 != PUNCH && state_player2 != JUMP) health_player2 <= health_player2 - 2;
        else if (state_player2 == PUNCH && state_player1 != PUNCH && state_player1 != JUMP) health_player1 <= health_player1 - 2;
        else if (state_player1 == KICK && state_player2 != KICK && state_player2 != JUMP) health_player2 <= health_player2 - 1;
        else if (state_player2 == KICK && state_player1 != KICK && state_player1 != JUMP) health_player1 <= health_player1 - 1;
        else if (state_player1 == PUNCH && state_player2 == PUNCH) begin
            // Both players perform the same attack, move to farthest positions
            position_player1 <= position_player1 - 1;  // Leftmost position for player 1
            position_player2 <= position_player2 + 1;  // Rightmost position for player 2
        end
        else if (state_player1 == KICK && state_player2 == KICK) begin
            // Both players perform the same attack, move to farthest positions
            position_player1 <= position_player1 - 1;  // Leftmost position for player 1
            position_player2 <= position_player2 + 1;  // Rightmost position for player 2
        end
    end

    if(position_player2 - position_player1 == 2) begin
        if (state_player1 == KICK && state_player2 != KICK && state_player2 != JUMP) health_player2 <= (health_player2 - 1);
        else if (state_player2 == KICK && state_player1 != KICK && state_player1 != JUMP) health_player1 <= (health_player1 - 1);
        else if (state_player1 == KICK && state_player2 == KICK) begin
            // Both players perform the same attack, move to farthest positions
            position_player1 <= position_player1 - 1;  // Leftmost position for player 1
            position_player2 <= position_player2 + 1;  // Rightmost position for player 2
        end
    end

    // Handling the wait logic for player 1
    if (state_player1 == WAIT && last_action_player1 == WAIT) begin
        if (health_player1 < 3) health_player1 <= health_player1 + 1;
    end
    last_action_player1 <= state_player1;  // Update last action

    // Handling the wait logic for player 2
    if (state_player2 == WAIT && last_action_player2 == WAIT) begin
        if (health_player2 < 3) health_player2 <= health_player2 + 1;
    end
    last_action_player2 <= state_player2;  // Update last action
end

endmodule

two_player_game_tb.v
`timescale 1ns / 1ps
`include "two_player_game.v"
module two_player_game_tb();

    // Declare the inputs and outputs
    reg clk, reset;
    reg [2:0] action_player1, action_player2;
    wire [1:0] health_player1, health_player2;
    wire [2:0] position_player1, position_player2;

    // Instantiate the two_player_game module
    two_player_game uut (
        .clk(clk),
        .reset(reset),
        .action_player1(action_player1),
        .action_player2(action_player2),
        .health_player1(health_player1),
        .health_player2(health_player2),
        .position_player1(position_player1),
        .position_player2(position_player2)
    );

    // Generate the reset signal
    initial begin
        reset = 1;
        clk = 0;
        #10;
        reset = 0;
        repeat(27) #10 clk = ~clk;
    end

    // Apply the test vectors
    initial begin
        $dumpfile("two_player_game_tb.vcd");
        $dumpvars(0, uut);
        #20;
        
        action_player1 = 3'b001;//move right
        action_player2 = 3'b000;//move left
        #20

        action_player1 = 3'b001;//move right
        action_player2 = 3'b000;//move left
        #20;

        
        action_player1 = 3'b100;//punch
        action_player2 = 3'b010;//jump
        #20;

        action_player1 = 3'b100;//punch
        action_player2 = 3'b101;//kick
        #20;

        action_player1 = 3'b100;//punch
        action_player2 = 3'b100;//punch
        #20;

        action_player1 = 3'b001;//move right
        action_player2 = 3'b011;//wait
        #20;

        action_player1 = 3'b010;//jump
        action_player2 = 3'b011;//wait
        #20;

        action_player1 = 3'b100;//punch
        action_player2 = 3'b101;//kick
        #20;

        action_player1 = 3'b101;//kick
        action_player2 = 3'b010;//jump
        #20;

        action_player1 = 3'b000;//move left
        action_player2 = 3'b101;//kick
        #20;

        action_player1 = 3'b101;//kick
        action_player2 = 3'b000;//move left
        #20;

    


    end

endmodule

two_player_game_tb.vcd
$date
	Sat Jan 27 19:17:29 2024
$end
$version
	Icarus Verilog
$end
$timescale
	1ps
$end
$scope module two_player_game_tb $end
$scope module uut $end
$var wire 3 ! action_player1 [2:0] $end
$var wire 3 " action_player2 [2:0] $end
$var wire 1 # clk $end
$var wire 1 $ reset $end
$var parameter 3 % JUMP $end
$var parameter 3 & KICK $end
$var parameter 3 ' MOVE_LEFT $end
$var parameter 3 ( MOVE_RIGHT $end
$var parameter 3 ) PUNCH $end
$var parameter 3 * WAIT $end
$var reg 2 + health_player1 [1:0] $end
$var reg 2 , health_player2 [1:0] $end
$var reg 3 - last_action_player1 [2:0] $end
$var reg 3 . last_action_player2 [2:0] $end
$var reg 3 / position_player1 [2:0] $end
$var reg 3 0 position_player2 [2:0] $end
$var reg 3 1 state_player1 [2:0] $end
$var reg 3 2 state_player2 [2:0] $end
$upscope $end
$upscope $end
$enddefinitions $end
$comment Show the parameter values. $end
$dumpall
b11 *
b100 )
b1 (
b0 '
b101 &
b10 %
$end
#0
$dumpvars
b11 2
b11 1
b101 0
b0 /
b11 .
b11 -
b11 ,
b11 +
1$
0#
bx "
bx !
$end
#10000
0$
#20000
b0 2
b1 1
1#
b0 "
b1 !
#30000
0#
#40000
b0 .
b1 -
b100 0
b1 /
1#
#50000
0#
#60000
b11 0
b10 /
b10 2
b100 1
1#
b10 "
b100 !
#70000
0#
#80000
b10 .
b100 -
b101 2
1#
b101 "
#90000
0#
#100000
b101 .
b1 ,
b100 2
1#
b100 "
#110000
0#
#120000
b100 .
b100 0
b1 /
b11 2
b1 1
1#
b11 "
b1 !
#130000
0#
#140000
b11 .
b1 -
b10 /
b10 1
1#
b10 !
#150000
0#
#160000
b10 ,
b10 -
b101 2
b100 1
1#
b101 "
b100 !
#170000
0#
#180000
b101 .
b100 -
b10 +
b10 2
b101 1
1#
b10 "
b101 !
#190000
0#
#200000
b10 .
b101 -
b101 2
b0 1
1#
b101 "
b0 !
#210000
0#
#220000
b101 .
b0 -
b1 +
b1 /
b0 2
b101 1
1#
b0 "
b101 !
#230000
0#
#240000
b0 .
b101 -
b11 0
1#
#250000
0#
#260000
b1 ,
1#
#270000
0#
#280000
b0 ,
1#
